topsis/__init__.py
topsis/topsis.py
topsis_Devansh_102218067-0.4.dist-info/METADATA
topsis_Devansh_102218067-0.4.dist-info/WHEEL
topsis_Devansh_102218067-0.4.dist-info/entry_points.txt
topsis_Devansh_102218067-0.4.dist-info/top_level.txt
topsis_Devansh_102218067-0.4.dist-info/RECORD
