Metadata-Version: 2.1
Name: topsis-Devansh-102218067
Version: 0.4
Summary: A Python package for TOPSIS
Author: Devansh Arya
Author-email: Dv30arya@gmail.com
License: MIT
Requires-Dist: numpy
Requires-Dist: pandas
Requires-Dist: argparse
Requires-Dist: scipy
